README.md
setup.py
Django_labeller.egg-info/PKG-INFO
Django_labeller.egg-info/SOURCES.txt
Django_labeller.egg-info/dependency_links.txt
Django_labeller.egg-info/not-zip-safe
Django_labeller.egg-info/requires.txt
Django_labeller.egg-info/top_level.txt
django_labeller.egg-info/PKG-INFO
django_labeller.egg-info/SOURCES.txt
django_labeller.egg-info/dependency_links.txt
django_labeller.egg-info/not-zip-safe
django_labeller.egg-info/requires.txt
django_labeller.egg-info/top_level.txt
image_labelling_tool/__init__.py
image_labelling_tool/admin.py
image_labelling_tool/apps.py
image_labelling_tool/flask_labeller.py
image_labelling_tool/labelled_image.py
image_labelling_tool/labelling_schema.py
image_labelling_tool/labelling_tool.py
image_labelling_tool/labelling_tool_views.py
image_labelling_tool/managers.py
image_labelling_tool/models.py
image_labelling_tool/schema_editor_messages.py
image_labelling_tool/schema_editor_views.py
image_labelling_tool/test_imagelabels.py
image_labelling_tool/test_label_classes.py
image_labelling_tool/test_objecttable.py
image_labelling_tool/tests.py
image_labelling_tool/management/__init__.py
image_labelling_tool/management/commands/__init__.py
image_labelling_tool/management/commands/update_label_object_ids.py
image_labelling_tool/migrations/0001_initial.py
image_labelling_tool/migrations/0002_labels_edit_time_elapsed.py
image_labelling_tool/migrations/0003_auto_20180911_0954.py
image_labelling_tool/migrations/0004_auto_20200223_1009.py
image_labelling_tool/migrations/0005_auto_20200825_1128.py
image_labelling_tool/migrations/0006_remove_labels_complete.py
image_labelling_tool/migrations/0007_auto_20210322_1737.py
image_labelling_tool/migrations/0008_auto_20210324_1416.py
image_labelling_tool/migrations/__init__.py
image_labelling_tool/static/Sortable-1.10.0-rc3.js
image_labelling_tool/static/bootstrap-4.3.1.min.css
image_labelling_tool/static/bootstrap-4.3.1.min.js
image_labelling_tool/static/d3.d.ts
image_labelling_tool/static/d3.min.js
image_labelling_tool/static/image_labeller.css
image_labelling_tool/static/jquery-3.6.0.min.js
image_labelling_tool/static/jquery.d.ts
image_labelling_tool/static/js.cookie.js
image_labelling_tool/static/json2.js
image_labelling_tool/static/polybool.min.js
image_labelling_tool/static/polyk.d.ts
image_labelling_tool/static/polyk.js
image_labelling_tool/static/popper-1.14.7.min.js
image_labelling_tool/static/socket.io.min.js
image_labelling_tool/static/spectrum.css
