Metadata-Version: 2.1
Name: django-labeller
Version: 0.3.1
Summary: An image labelling tool for creating segmentation data sets, for Django, Flask and Qt.
Home-page: https://github.com/Britefury/django-labeller
Author: Geoff French
License: MIT
Platform: UNKNOWN
Classifier: Development Status :: 3 - Alpha
Classifier: Intended Audience :: Developers
Classifier: Intended Audience :: Science/Research
Classifier: License :: OSI Approved :: MIT License
Classifier: Programming Language :: Python :: 3.6
Classifier: Topic :: Software Development :: User Interfaces
Provides-Extra: testing
Provides-Extra: django
Provides-Extra: dextr
Provides-Extra: qt5
